crlite_status/__init__.py
crlite_status/status.py
crlite_status/status_test.py
crlite_status-0.0.8.dist-info/METADATA
crlite_status-0.0.8.dist-info/WHEEL
crlite_status-0.0.8.dist-info/entry_points.txt
crlite_status-0.0.8.dist-info/licenses/LICENSE
crlite_status-0.0.8.dist-info/RECORD
