Metadata-Version: 2.3
Name: crlite_status
Version: 0.0.8
Summary: Use this tool get information about recent CRLite runs
Project-URL: Repository, http://github.com/jcjones/crlite_status
Maintainer-email: "J.C. Jones" <jc@insufficient.coffee>
License: Mozilla Public License Version 2.0
License-File: LICENSE
Keywords: bloom filter,cascade,crlite,mlbf,multi level
Classifier: Development Status :: 4 - Beta
Classifier: License :: OSI Approved :: Mozilla Public License 2.0 (MPL 2.0)
Classifier: Programming Language :: Python :: 3
Requires-Python: >=3.7
Requires-Dist: requests>=2.10
Requires-Dist: rich>=3.0
